s3_wrapper/__init__.py
s3_wrapper/exceptions.py
s3_wrapper/utils.py
s3_wrapper-0.0.6.dist-info/LICENSE
s3_wrapper-0.0.6.dist-info/METADATA
s3_wrapper-0.0.6.dist-info/WHEEL
s3_wrapper-0.0.6.dist-info/top_level.txt
s3_wrapper-0.0.6.dist-info/RECORD
