Metadata-Version: 2.1
Name: s3-wrapper
Version: 0.0.6
Summary: Utilities for AWS S3
Home-page: https://github.com/citibeats-labs/s3-utils
Author: Citibeats Labs
Author-email: labs@citibeats.net
License: UNKNOWN
Platform: UNKNOWN
Classifier: Programming Language :: Python :: 3
Classifier: License :: OSI Approved :: GNU General Public License v3 (GPLv3)
Classifier: Operating System :: OS Independent
Requires-Python: >=3.7
Requires-Dist: boto3
